tubular/__init__.py
tubular/_checks.py
tubular/_stats.py
tubular/_utils.py
tubular/aggregations.py
tubular/base.py
tubular/capping.py
tubular/comparison.py
tubular/dates.py
tubular/imputers.py
tubular/mapping.py
tubular/misc.py
tubular/mixins.py
tubular/nominal.py
tubular/numeric.py
tubular/pipeline.py
tubular/strings.py
tubular/types.py
tubular-2.7.0.dist-info/licenses/LICENSE
tubular-2.7.0.dist-info/METADATA
tubular-2.7.0.dist-info/WHEEL
tubular-2.7.0.dist-info/top_level.txt
tubular-2.7.0.dist-info/RECORD
