Metadata-Version: 2.4
Name: tubular
Version: 2.7.0
Summary: Python package implementing ML feature engineering and pre-processing for polars or pandas dataframes.
Author-email: Allianz UK Data Science Team <datasciencepackages@allianz.co.uk>
License: BSD 3-Clause License
Project-URL: Documentation, https://tubular.readthedocs.io/en/latest/index.html
Project-URL: Repository, https://github.com/azukds/tubular
Project-URL: Issues, https://github.com/azukds/tubular/issues
Project-URL: Changelog, https://github.com/azukds/tubular/CHANGELOG.md
Keywords: polars,pandas,feature engineering,pre-processing,machine learning,ML,data science,data transforms,pipeline,sklearn,DS
Classifier: Programming Language :: Python
Classifier: Programming Language :: Python :: 3.9
Classifier: Programming Language :: Python :: 3.10
Classifier: Programming Language :: Python :: 3.11
Classifier: Programming Language :: Python :: 3.12
Classifier: Operating System :: OS Independent
Classifier: License :: OSI Approved :: BSD License
Requires-Python: >=3.9
License-File: LICENSE
Requires-Dist: pandas>=1.5.0
Requires-Dist: scikit-learn>=1.2.0
Requires-Dist: narwhals>=2.11.0
Requires-Dist: polars>=1.9.0
Requires-Dist: beartype>=0.19.0
Requires-Dist: typing-extensions>=4.5.0
Provides-Extra: dev
Requires-Dist: test-aide>=0.1.0; extra == "dev"
Requires-Dist: pytest>=5.4.1; extra == "dev"
Requires-Dist: pytest-mock>=3.5.1; extra == "dev"
Requires-Dist: pyarrow>=17.0.0; extra == "dev"
Requires-Dist: pytest-cov<=2.10.1; extra == "dev"
Requires-Dist: prek; extra == "dev"
Requires-Dist: ruff>=0.2.2; extra == "dev"
Requires-Dist: auto-walrus==0.3.4; extra == "dev"
Requires-Dist: tabulate>=0.9.0; extra == "dev"
Requires-Dist: codespell; extra == "dev"
Requires-Dist: typos; extra == "dev"
Requires-Dist: blacken-docs; extra == "dev"
Dynamic: license-file
